lcgttest/__init__.py
lcgttest/lcgttest.py
lcgeuclideanmethod-0.1.0.dist-info/METADATA
lcgeuclideanmethod-0.1.0.dist-info/WHEEL
lcgeuclideanmethod-0.1.0.dist-info/top_level.txt
lcgeuclideanmethod-0.1.0.dist-info/RECORD
