Metadata-Version: 2.1
Name: lcgeuclideanmethod
Version: 0.1.0
Summary: Determining LCG population from campaign takers/non by calculating Euclidean Method and ttest
Home-page: UNKNOWN
Author: Azka Rohbiya Ramadan
Author-email: azkarohbiya@gmail.com
License: UNKNOWN
Platform: UNKNOWN
Requires-Python: >=3.1
Requires-Dist: pandas (>=1.1.5)
Requires-Dist: numpy (>=1.18.5)
Requires-Dist: scipy (>=1.2.0)
Requires-Dist: matplotlib (>=3.1.0)
Requires-Dist: statsmodels (>=0.8.0)
